domain_validator/__init__.py
domain_validator/cli.py
domain_validator/domain_validator.py
domain_validator-0.1.0.dist-info/METADATA
domain_validator-0.1.0.dist-info/WHEEL
domain_validator-0.1.0.dist-info/RECORD
