Metadata-Version: 2.3
Name: domain-validator
Version: 0.1.0
Summary: Domain name validation package for Python
Author: Stacy Noland
Author-email: stacy.noland@outlook.com
Requires-Python: >=3.13
Classifier: Development Status :: 3 - Alpha
Classifier: Intended Audience :: Developers
Classifier: Intended Audience :: Information Technology
Classifier: License :: OSI Approved :: MIT License
Classifier: Operating System :: OS Independent
Classifier: Programming Language :: Python
Classifier: Programming Language :: Python :: 3
Classifier: Programming Language :: Python :: 3 :: Only
Classifier: Programming Language :: Python :: 3.9
Classifier: Programming Language :: Python :: 3.10
Classifier: Programming Language :: Python :: 3.11
Classifier: Programming Language :: Python :: 3.12
Classifier: Programming Language :: Python :: 3.13
Classifier: Topic :: Internet :: Name Service (DNS)
Classifier: Topic :: Software Development :: Libraries
Classifier: Topic :: Software Development :: Libraries :: Python Modules
Classifier: Typing :: Typed
Provides-Extra: cli
Requires-Dist: dnspython (>=2.7.0,<3.0.0)
Requires-Dist: typer (>=0.15.2,<1.0.0) ; extra == "cli"
